mapclient/__init__.py
mapclient/application.py
mapclient/exceptions.py
mapclient/splash_rc.py
mapclient/splashscreen.py
mapclient/core/__init__.py
mapclient/core/annotations.py
mapclient/core/checks.py
mapclient/core/exitcodes.py
mapclient/core/importexport.py
mapclient/core/mainapplication.py
mapclient/core/metrics.py
mapclient/core/pluginframework.py
mapclient/core/provenance.py
mapclient/core/utils.py
mapclient/core/managers/__init__.py
mapclient/core/managers/optionsmanager.py
mapclient/core/managers/packagemanager.py
mapclient/core/managers/pluginmanager.py
mapclient/core/managers/undomanager.py
mapclient/core/managers/workflowmanager.py
mapclient/core/workflow/__init__.py
mapclient/core/workflow/workflowdependencygraph.py
mapclient/core/workflow/workflowerror.py
mapclient/core/workflow/workflowitems.py
mapclient/core/workflow/workflowrdf.py
mapclient/core/workflow/workflowscene.py
mapclient/core/workflow/workflowsteps.py
mapclient/core/workflow/workflowutils.py
mapclient/core/workflow/layouts/__init__.py
mapclient/core/workflow/layouts/forcedirected.py
mapclient/core/workflow/layouts/springforce.py
mapclient/mountpoints/__init__.py
mapclient/mountpoints/menuoption.py
mapclient/mountpoints/stackedwidget.py
mapclient/mountpoints/workflowstep.py
mapclient/settings/__init__.py
mapclient/settings/definitions.py
mapclient/settings/general.py
mapclient/settings/info.py
mapclient/settings/version.py
mapclient/tools/__init__.py
mapclient/tools/annotation/__init__.py
mapclient/tools/annotation/annotation.voc
mapclient/tools/annotation/annotationdialog.py
mapclient/tools/annotation/annotationtool.py
mapclient/tools/annotation/ui/__init__.py
mapclient/tools/annotation/ui/ui_annotationdialog.py
mapclient/tools/mapicon/__init__.py
mapclient/tools/mapicon/mapicondialog.py
mapclient/tools/mapicon/ui/__init__.py
mapclient/tools/mapicon/ui/ui_mapicondialog.py
mapclient/tools/osxapp/__init__.py
mapclient/tools/osxapp/mapclient.icns
mapclient/tools/osxapp/shimbundle.py
mapclient-0.25.0.dist-info/licenses/LICENSE
mapclient-0.25.0.dist-info/licenses/NOTICE
mapclient-0.25.0.dist-info/METADATA
mapclient-0.25.0.dist-info/WHEEL
mapclient-0.25.0.dist-info/entry_points.txt
mapclient-0.25.0.dist-info/top_level.txt
mapclient-0.25.0.dist-info/RECORD
