Metadata-Version: 2.4
Name: mapclient
Version: 0.25.0
Summary: A framework for managing and sharing workflows.
Home-page: https://github.com/MusculoskeletalAtlasProject/mapclient
Author: MAP Client Developers
Author-email: mapclient-devs@physiomeproject.org
License-File: LICENSE
License-File: NOTICE
Requires-Dist: PySide6!=6.7.0,>=6.5
Requires-Dist: rdflib
Requires-Dist: virtualenv
Requires-Dist: requests
Requires-Dist: python-dateutil
Requires-Dist: dulwich!=0.22.0
Requires-Dist: pmr2.wfctrl>=0.6.0
Requires-Dist: pmr2.client>=0.2
Requires-Dist: packaging
Requires-Dist: filelock
Requires-Dist: psutil>=6.0
Requires-Dist: PyGithub
Requires-Dist: numpy
Provides-Extra: dev
Requires-Dist: PyInstaller; extra == "dev"
Dynamic: author
Dynamic: author-email
Dynamic: description
Dynamic: description-content-type
Dynamic: home-page
Dynamic: license-file
Dynamic: provides-extra
Dynamic: requires-dist
Dynamic: summary
